{
  "date": "2026-06-22",
  "total_extracted": 1769,
  "total_new": 196,
  "total_existing": 1573,
  "articles": [
    {
      "title": "President João Lourenço swears in new vice-governor of Cuanza-Norte",
      "url": "https://www.angop.ao/en/noticias/politica/pr-empossa-novo-vice-governador-do-cuanza-norte/",
      "source": "ANGOP",
      "_key": "208dc1aa09ceba6e"
    },
    {
      "title": "Cidadela Stadium second tier of the west stand collapses",
      "url": "https://www.angop.ao/en/noticias/desporto/parte-da-bancada-do-estadio-da-cidadela-desaba/",
      "source": "ANGOP",
      "_key": "a29f2ae2e9f1930f"
    },
    {
      "title": "INADE Director-General highlights national exams impact on admission tests",
      "url": "https://www.angop.ao/en/noticias/entrevistas/inade-ressalta-impacto-dos-exames-nacionais-nos-testes-de-admissao/",
      "source": "ANGOP",
      "_key": "85f4980468263983"
    },
    {
      "title": "Police thwart shipment of over 80 million kwanzas to DRC",
      "url": "https://www.angop.ao/en/noticias/economia/policia-trava-saida-de-mais-de-80-milhoes-de-kwanzas-para-rdc/",
      "source": "ANGOP",
      "_key": "34ff9a9baf3f3a0e"
    },
    {
      "title": "Customers in Lunda-Sul owe five billion kwanzas to electricity supplier company",
      "url": "https://www.angop.ao/en/noticias/sociedade/clientes-da-lunda-sul-devem-cinco-mil-milhoes-de-kwanzas-a-ende/",
      "source": "ANGOP",
      "_key": "bc9d4001c571d9d6"
    },
    {
      "title": "Angolan Foreign Minister calls for the implementation of agreements between universities",
      "url": "https://www.angop.ao/en/noticias/politica/tete-antonio-apela-a-implementacao-dos-acordos-entre-universidades/",
      "source": "ANGOP",
      "_key": "f25df7a03305d26c"
    },
    {
      "title": "Infracção",
      "url": "https://www.angop.ao/en/assuntos-relacionados/?varea=1&vtab=113520",
      "source": "ANGOP",
      "_key": "9e078cd3aac9bcbb"
    },
    {
      "title": "Head of State makes private visit to Brazil",
      "url": "https://www.angop.ao/en/noticias/politica/joao-lourenco-efectua-visita-privada-ao-brasil/",
      "source": "ANGOP",
      "_key": "17f96315d3762afb"
    },
    {
      "title": "Angolan Ambassador to Cuba passes away",
      "url": "https://www.angop.ao/en/noticias/politica/faleceu-embaixador-de-angola-em-cuba-carlos-sardinha-dias/",
      "source": "ANGOP",
      "_key": "e41a2ab017767a7e"
    },
    {
      "title": "Falecimento",
      "url": "https://www.angop.ao/en/assuntos-relacionados/?varea=1&vtab=264875",
      "source": "ANGOP",
      "_key": "34e70539854d1281"
    },
    {
      "title": "Politicians praise victims of armed conflicts tribute",
      "url": "https://www.angop.ao/en/noticias/politica/politicos-elogiam-plano-de-homenagem-as-vitimas-de-conflitos-armados/",
      "source": "ANGOP",
      "_key": "f007b56d49cb2b4b"
    },
    {
      "title": "CIVICOP",
      "url": "https://www.angop.ao/en/assuntos-relacionados/?varea=1&vtab=41687",
      "source": "ANGOP",
      "_key": "8818587bf71c947a"
    },
    {
      "title": "Luanda to host first judicial dialogue between Angola and Brazil",
      "url": "https://www.angop.ao/en/noticias/politica/luanda-acolhe-primeiro-dialogo-judicial-entre-angola-e-brasil/",
      "source": "ANGOP",
      "_key": "be863d040471683a"
    },
    {
      "title": "Aliko Dangote attends African Sovereign Wealth Fund gathering in Angola",
      "url": "https://www.angop.ao/en/noticias/economia/aliko-dangote-marca-presenca-no-forum-dos-fundos-soberanos-africanos-em-angola/",
      "source": "ANGOP",
      "_key": "26a8197744931de8"
    },
    {
      "title": "Moxico Leste to host 6th advisory council of industry and commerce",
      "url": "https://www.angop.ao/en/noticias/economia/moxico-leste-acolhe-sexto-conselho-consultivo-do-ministerio-da-industria-e-comercio/",
      "source": "ANGOP",
      "_key": "b73c4d80e418e95e"
    },
    {
      "title": "Conselho Consultivo",
      "url": "https://www.angop.ao/en/assuntos-relacionados/?varea=1&vtab=42155",
      "source": "ANGOP",
      "_key": "ea67d8a4c3148c9d"
    },
    {
      "title": "TUI Hotels & Resorts delegation visits Angola tourist destinations",
      "url": "https://www.angop.ao/en/noticias/turismo/delegacao-da-tui-hotels-resorts-visita-destinos-turisticos-em-angola/",
      "source": "ANGOP",
      "_key": "8cb01ad7155ee6ce"
    },
    {
      "title": "Angola presents products at Swiss-African Business Day",
      "url": "https://www.angop.ao/en/noticias/economia/angola-apresenta-produtos-no-dia-empresarial-suico-africano/",
      "source": "ANGOP",
      "_key": "febfd078893ac5f5"
    },
    {
      "title": "ecomomia",
      "url": "https://www.angop.ao/en/assuntos-relacionados/?varea=1&vtab=171197",
      "source": "ANGOP",
      "_key": "d84790a70a764096"
    },
    {
      "title": "SODIAM holds online auction of 35 special diamonds",
      "url": "https://www.angop.ao/en/noticias/economia/sodiam-realiza-leilao-online-de-35-pedras-especiais-de-diamante/",
      "source": "ANGOP",
      "_key": "3541195affead1bb"
    },
    {
      "title": "Leilão",
      "url": "https://www.angop.ao/en/assuntos-relacionados/?varea=1&vtab=40169",
      "source": "ANGOP",
      "_key": "234e378cfbe8cc81"
    },
    {
      "title": "Recreativo da Caála becomes champion of 2nd division football tournament",
      "url": "https://www.angop.ao/en/noticias/desporto/recreativo-da-caala-e-campeao-da-2xa-divisao/",
      "source": "ANGOP",
      "_key": "fa9fae432414af9e"
    },
    {
      "title": "Handball: Junior National Team competes in World Championship in China",
      "url": "https://www.angop.ao/en/noticias/desporto/andebol-seleccao-de-juniores-disputa-mundial-na-china/",
      "source": "ANGOP",
      "_key": "596a6f35443cf47b"
    },
    {
      "title": "Sailing: Angola competes in the Optimist World Championship in Morocco",
      "url": "https://www.angop.ao/en/noticias/desporto/vela-angola-compete-no-mundial-de-optimist-no-marrocos/",
      "source": "ANGOP",
      "_key": "f703674b78bde44d"
    },
    {
      "title": "Physician presents Hospital in a Box project at Ministry of Health",
      "url": "https://www.angop.ao/en/noticias/saude/saude-recebe-apresentacao-do-projecto-hospital-em-uma-caixa/",
      "source": "ANGOP",
      "_key": "8fb93e7a00b14853"
    },
    {
      "title": "SPCB reports 6 deaths over the weekend",
      "url": "https://www.angop.ao/en/noticias/sociedade/bombeiros-registam-seis-mortes-no-fim-de-semana-em-angola/",
      "source": "ANGOP",
      "_key": "44b11d918dff0dba"
    },
    {
      "title": "Over 600 schools to hold national exams in Angola",
      "url": "https://www.angop.ao/en/noticias/educacao/exames-nacionais-decorrem-em-690-escolas-em-angola/",
      "source": "ANGOP",
      "_key": "877d2f3b97ee03b6"
    },
    {
      "title": "Angolan specialist completes training at Massachusetts Institute of Technology",
      "url": "https://www.angop.ao/en/noticias/sociedade/especialista-angolano-conclui-programa-no-mit/",
      "source": "ANGOP",
      "_key": "a30b5d943f25af96"
    },
    {
      "title": "Evangelical Church to offer university scholarships to prisoners in Huíla",
      "url": "https://www.angop.ao/en/noticias/educacao/iesa-promete-bolsas-de-estudo-universitarias-para-reclusos-na-huila/",
      "source": "ANGOP",
      "_key": "058a2ea36dcfbb66"
    },
    {
      "title": "Health Ministry promotes humanization week for quality care",
      "url": "https://www.angop.ao/en/noticias/saude/minsa-promove-semana-nacional-da-humanizacao-para-qualidade-no-atendimento/",
      "source": "ANGOP",
      "_key": "23b99d1274c35626"
    },
    {
      "title": "Primeiro-ministro do Reino Unido, Keir Starmer, renuncia ao cargo",
      "url": "https://angola24horas.com/internacional/item/34541-primeiro-ministro-do-reino-unido-keir-starmer-renuncia-ao-cargo",
      "source": "Angola 24 Horas",
      "_key": "88f0fe0c6548b732"
    },
    {
      "title": "Adalberto Costa Júnior apela ao diálogo e defende alternância democrática em Angola",
      "url": "https://angola24horas.com/component/k2/item/34542-adalberto-costa-junior-apela-ao-dialogo-e-defende-alternancia-democratica-em-angola",
      "source": "Angola 24 Horas",
      "_key": "c35a96772011e970"
    },
    {
      "title": "ONG condena alegado ataque contra ativistas cívicos em Malanje",
      "url": "https://angola24horas.com/sociedade/item/34543-ong-condena-alegado-ataque-contra-ativistas-civicos-em-malanje",
      "source": "Angola 24 Horas",
      "_key": "4c5948c3e909effc"
    },
    {
      "title": "Sobreviventes do 27 de Maio em Angola acham os próprios nomes em lista de mortos da Civicop",
      "url": "https://angola24horas.com/politica/item/34540-sobreviventes-do-27-de-maio-em-angola-acham-os-proprios-nomes-em-lista-de-mortos-da-civicop",
      "source": "Angola 24 Horas",
      "_key": "718584db7e409483"
    },
    {
      "title": "Bloco Democrático denuncia falta de resposta do Ministério do Interior a pedido de visita humanitária a detidos",
      "url": "https://www.club-k.net/index.php?option=com_content&view=article&id=60552:bloco-democratico-denuncia-falta-de-resposta-do-ministerio-do-interior-a-pedido-de-visita-humanitaria-a-detidos&catid=23:politica&lang=pt&Itemid=641",
      "source": "Club K",
      "_key": "db47eedd6a25ba6b"
    },
    {
      "title": "Angola: Famílias em projetos habitacionais clamam por serviços básicos",
      "url": "https://www.dw.com/pt-002/angola-famílias-em-projetos-habitacionais-clamam-por-serviços-básicos/a-77657971?maca=por-RSS_VAF_Club-K-22869-xml-cb",
      "source": "Club K",
      "_key": "feb94a55334d3b3f"
    },
    {
      "title": "Morreu ex-presidente de Timor-Leste Francisco Guterres \"Lu Olo\"",
      "url": "https://www.dw.com/pt-002/morreu-ex-presidente-de-timor-leste-francisco-guterres-lu-olo/a-77648460?maca=por-RSS_VAF_Club-K-22869-xml-cb",
      "source": "Club K",
      "_key": "b9ffa75245a5297a"
    },
    {
      "title": "Irão: JD Vance saúda \"encontro histórico\" e quer \"mudança permanente\" nas relações na região",
      "url": "https://www.dw.com/pt-002/irão-jd-vance-saúda-encontro-histórico-e-quer-mudança-permanente-nas-relações-na-região/a-77647251?maca=por-RSS_VAF_Club-K-22869-xml-cb",
      "source": "Club K",
      "_key": "d29e7d76352e277f"
    },
    {
      "title": "MPLA em Luanda intensifica dinâmica política nos municípios para os desafios de 2027",
      "url": "https://correiokianda.info/mpla-em-luanda-intensifica-dinamica-politica-nos-municipios-para-os-desafios-de-2027/",
      "source": "Correio Kianda",
      "_key": "bb16fdb52ea7710d"
    },
    {
      "title": "Presidente João Lourenço realiza visita de carácter privado ao Brasil",
      "url": "https://correiokianda.info/presidente-joao-lourenco-realiza-visita-de-caracter-privado-ao-brasil/",
      "source": "Correio Kianda",
      "_key": "0b3a9c53469d4df5"
    },
    {
      "title": "Comunicações e inovação digital aproximam Angola e Moçambique",
      "url": "https://correiokianda.info/comunicacoes-e-inovacao-digital-aproximam-angola-e-mocambique/",
      "source": "Correio Kianda",
      "_key": "551b1bd99360dc72"
    },
    {
      "title": "OMA promove jornada patriótica no Bié enquanto LIMA mobiliza militantes no Cazenga",
      "url": "https://correiokianda.info/oma-promove-jornada-patriotica-no-bie-enquanto-lima-mobiliza-militantes-no-cazenga/",
      "source": "Correio Kianda",
      "_key": "a58a81c5d89da701"
    },
    {
      "title": "Especialistas defendem maior transparência dos partidos na gestão das verbas das eleições",
      "url": "https://correiokianda.info/especialistas-defendem-maior-transparencia-dos-partidos-na-gestao-das-verbas-das-eleicoes/",
      "source": "Correio Kianda",
      "_key": "19a9599f59aa4fc8"
    },
    {
      "title": "Mais de 457 mil barris produzidos e 103 mil transferidos marcam avanço da Refinaria de Cabinda",
      "url": "https://correiokianda.info/mais-de-457-mil-barris-produzidos-e-103-mil-transferidos-marcam-avanco-da-refinaria-de-cabinda/",
      "source": "Correio Kianda",
      "_key": "b974ecacea19275d"
    },
    {
      "title": "Câmara de Comércio realiza censo para avaliar impacto das empresas chinesas na economia Angolana",
      "url": "https://correiokianda.info/camara-de-comercio-realiza-censo-para-avaliar-impacto-das-empresas-chinesas-na-economia-angolana/",
      "source": "Correio Kianda",
      "_key": "ced3b5b94a8753e1"
    },
    {
      "title": "Especialistas pedem cautela na aplicação de novos impostos em Angola",
      "url": "https://correiokianda.info/especialistas-pedem-cautela-na-aplicacao-de-novos-impostos-em-angola/",
      "source": "Correio Kianda",
      "_key": "f65776c2f5917e3a"
    },
    {
      "title": "Mulher mata marido à facada após desentendimento conjugal em Viana",
      "url": "https://correiokianda.info/mulher-mata-marido-a-facada-apos-desentendimento-conjugal-em-viana/",
      "source": "Correio Kianda",
      "_key": "cfd26a23f839e78d"
    },
    {
      "title": "Regresso da alimentação escolar devolve alunos às salas de aula no Cuvango",
      "url": "https://correiokianda.info/regresso-da-merenda-escolar-devolve-alunos-as-salas-de-aula-no-cuvango/",
      "source": "Correio Kianda",
      "_key": "8c50f801e9319d7e"
    },
    {
      "title": "Mais de sete mil vagas abertas para forças do Ministério do Interior",
      "url": "https://correiokianda.info/mais-de-sete-mil-vagas-abertas-para-forcas-do-ministerio-do-interior/",
      "source": "Correio Kianda",
      "_key": "35123596895a9ee4"
    },
    {
      "title": "Morre embaixador de Angola em Cuba, Carlos Sardinha Dias, aos 64 anos",
      "url": "https://correiokianda.info/morre-embaixador-de-angola-em-cuba-carlos-sardinha-dias-aos-64-anos/",
      "source": "Correio Kianda",
      "_key": "36fc26d4ebfeef73"
    },
    {
      "title": "Vandalismo na rede eléctrica preocupa autoridades de Talatona",
      "url": "https://correiokianda.info/vandalismo-na-rede-electrica-preocupa-autoridades-de-talatona/",
      "source": "Correio Kianda",
      "_key": "8c2446318ed3f271"
    },
    {
      "title": "Maus resultados eleitorais precipitam saída de Starmer do Governo britânico",
      "url": "https://correiokianda.info/maus-resultados-eleitorais-precipitam-saida-de-starmer-do-governo-britanico/",
      "source": "Correio Kianda",
      "_key": "6da4387c0546bfb8"
    },
    {
      "title": "França sob Alerta Vermelho por Calor Extremo",
      "url": "https://correiokianda.info/franca-sob-alerta-vermelho-por-calor-extremo/",
      "source": "Correio Kianda",
      "_key": "8aa04e3b4cd25867"
    },
    {
      "title": "Tensão política aumenta na RDC após declarações de Félix Tshisekedi e debate sobre revisão constitucional",
      "url": "https://correiokianda.info/tensao-politica-aumenta-na-rdc-apos-declaracoes-de-felix-tshisekedi-e-debate-sobre-revisao-constitucional/",
      "source": "Correio Kianda",
      "_key": "37aaef0af8c7d80a"
    },
    {
      "title": "Portugal anuncia criação de fundo soberano para investir em sectores estratégicos",
      "url": "https://correiokianda.info/portugal-anuncia-criacao-de-fundo-soberano-para-investir-em-sectores-estrategicos/",
      "source": "Correio Kianda",
      "_key": "81b0cf52ce9d2c9f"
    },
    {
      "title": "RDC: Arquidiocese de Kinshasa denuncia ocupação de espaço da igreja por militantes do partido no poder",
      "url": "https://correiokianda.info/rdc-arquidiocese-de-kinshasa-denuncia-ocupacao-de-espaco-da-igreja-por-militantes-do-partido-no-poder/",
      "source": "Correio Kianda",
      "_key": "8c9cd7dc184aee64"
    },
    {
      "title": "Egipto conquista primeira vitória da sua história em campeonatos do mundo",
      "url": "https://correiokianda.info/egipto-conquista-primeira-vitoria-da-sua-historia-em-campeonatos-do-mundo/",
      "source": "Correio Kianda",
      "_key": "23980433f17299f2"
    },
    {
      "title": "Desorganização atinge Balneário do Senegal por causa de alojamento e alimentos precários no mundial das Américas",
      "url": "https://correiokianda.info/desorganizacao-atinge-balneario-do-senegal-por-causa-de-alojamento-e-alimentos-precarios-no-mundial-das-americas/",
      "source": "Correio Kianda",
      "_key": "f5446ef317810fdf"
    },
    {
      "title": "Cabo Verde empata com Uruguai e mantém vivo o sonho do apuramento",
      "url": "https://correiokianda.info/cabo-verde-empata-com-uruguai-e-mantem-vivo-o-sonho-do-apuramento/",
      "source": "Correio Kianda",
      "_key": "73247874d2d4c1c3"
    },
    {
      "title": "Parte da bancada do Estádio da Cidadela desaba",
      "url": "https://correiokianda.info/parte-da-bancada-do-estadio-da-cidadela-desaba/",
      "source": "Correio Kianda",
      "_key": "c1daf8e86f3e67d6"
    },
    {
      "title": "Selecção de andebol Sub-20 já está na China para disputar Mundial feminino",
      "url": "https://correiokianda.info/seleccao-de-andebol-sub-20-ja-esta-na-china-para-disputar-mundial-feminino/",
      "source": "Correio Kianda",
      "_key": "c304e4574b91f56b"
    },
    {
      "title": "        Sociedade3 horas atrás  Autoridades sanitárias denunciam rejeição da vacina contra cólera em Cacuaco As autoridades sanitárias em Luanda lamentam a rejeição da vacina contra cólera no município de Cacuaco, um local que se apresenta como o epicentro da doença...   ",
      "url": "https://correiokianda.info/autoridades-sanitarias-denunciam-rejeicao-da-vacinacao-contra-colera-em-cacuaco/",
      "source": "Correio Kianda",
      "_key": "525ef087819cefa1"
    },
    {
      "title": "Mota-Engil Angola abre candidaturas para a 4.ª edição do Prémio Manuel António da Mota",
      "url": "https://diariodosnegocios.com/mota-engil-angola-abre-candidaturas-para-a-4-a-edicao-do-premio-manuel-antonio-da-mota/",
      "source": "Diário dos Negócios",
      "_key": "7d775328c9d9c202"
    },
    {
      "title": " Mota-Engil Angola abre candidaturas para a 4.ª edição do Prémio Manuel António da Mota ",
      "url": "",
      "source": "Diário dos Negócios",
      "_key": "t_0c917e9faa267e"
    },
    {
      "title": "Investigação associa a Angola empresa suspeita de interferência em eleições",
      "url": "",
      "source": "Expansão",
      "_key": "t_b00562baebb831"
    },
    {
      "title": "Oito em cada 10 obras estavam paralisadas no primeiro trimestre",
      "url": "",
      "source": "Expansão",
      "_key": "t_c8bbb3d73676e8"
    },
    {
      "title": "Feira da Liberdade facturava mais de 19 milhões Kz mensais",
      "url": "",
      "source": "Expansão",
      "_key": "t_e03f606ff0eb66"
    },
    {
      "title": "Keir Starmer demite-se e Reino Unido caminha para o sétimo primeiro-ministro em dez anos",
      "url": "https://expansao.co.ao/mundo/detalhe/keir-starmer-demite-se-e-reino-unido-caminha-para-o-setimo-primeiro-ministro-em-dez-anos-72720.html",
      "source": "Expansão",
      "_key": "64ff1f298f907285"
    },
    {
      "title": "Sodiam lança leilão online de 35 diamantes especiais com mais de 10,8 quilates",
      "url": "https://expansao.co.ao/empresas/detalhe/sodiam-lanca-leilao-online-de-35-diamantes-especiais-com-mais-de-108-quilates-72714.html",
      "source": "Expansão",
      "_key": "6b7989204fadc76a"
    },
    {
      "title": "Oito seguradoras lideram o ranking de transparência na prestação de contas",
      "url": "",
      "source": "Expansão",
      "_key": "t_735a581b41ad44"
    },
    {
      "title": "\"Olho para a exposição fotográfica em Angola como um investimento sem retorno\"",
      "url": "",
      "source": "Expansão",
      "_key": "t_1dd1aa45cc8721"
    },
    {
      "title": "Petróleo recua com sinais de avanço nas negociações entre Washington e Teerão",
      "url": "https://expansao.co.ao/economia/detalhe/petroleo-recua-com-sinais-de-avanco-nas-negociacoes-entre-washington-e-teerao-72712.html",
      "source": "Expansão",
      "_key": "0ee7e227c8cef3e9"
    },
    {
      "title": "Famílias angolanas arrancam o ano menos pessimistas face à evolução da economia",
      "url": "https://expansao.co.ao/economia/detalhe/familias-angolanas-arrancam-o-ano-menos-pessimistas-face-a-evolucao-da-economia-72707.html",
      "source": "Expansão",
      "_key": "a6cbf9ea70fcc3e6"
    },
    {
      "title": "Oito seguradoras lideram o ranking de transparência na prestação de contasO número de seguradoras com os pontos máximos atribuidos pelo Expansão duplicaram de quatro em 2022 para oito em 2025. Há cada vez mais seguradoras a adoptarem o caminho da transparência e das boas práticas. A NOSSA é o \"Real Madrid\" das seguradoras angolanas, já que é a que mais prémios ouro alcançou.",
      "url": "https://expansao.co.ao/empresas/detalhe/oito-seguradoras-lideram-o-ranking-de-transparencia-na-prestacao-de-contas-72706.html",
      "source": "Expansão",
      "_key": "ccc1e57e011f3dd0"
    },
    {
      "title": "Diplomacia angolana perde embaixador Carlos Sardinha Dias",
      "url": "https://forbesafricalusofona.com/diplomacia-angolana-perde-embaixador-carlos-sardinha-dias/",
      "source": "Forbes África",
      "_key": "4373d1e6c30e1682"
    },
    {
      "title": "Ulisses Correia e Silva diz que vai continuar a vida fora da política activa",
      "url": "https://forbesafricalusofona.com/ulisses-correia-e-silva-diz-que-vai-continuar-a-vida-fora-da-politica-activa/",
      "source": "Forbes África",
      "_key": "2d0abb9f3ba8cc1c"
    },
    {
      "title": "TUI Hotels & Resorts poderá investir no Polo de Desenvolvimento de Calandula",
      "url": "https://forbesafricalusofona.com/tui-hotels-resorts-podera-investir-no-polo-de-desenvolvimento-de-calandula/",
      "source": "Forbes África",
      "_key": "7b21c51a444d260d"
    },
    {
      "title": "Moçambique pretende introduzir tecnologia 5G até 2030",
      "url": "https://forbesafricalusofona.com/mocambique-pretende-introduzir-tecnologia-5g-ate-2030/",
      "source": "Forbes África",
      "_key": "c3efffbfa2586200"
    },
    {
      "title": "Crédito à economia moçambicana cai para 3,947 milhões de euros em Abril",
      "url": "https://forbesafricalusofona.com/credito-a-economia-mocambicana-cai-para-3947-milhoes-de-euros-em-abril/",
      "source": "Forbes África",
      "_key": "03dc871998be5175"
    },
    {
      "title": "Números de visitantes em Macau regista crescimento de 3,4% em Maio",
      "url": "https://forbesafricalusofona.com/numeros-de-visitantes-em-macau-regista-crescimento-de-34-em-maio/",
      "source": "Forbes África",
      "_key": "6f422a5db9563950"
    },
    {
      "title": "SODIAM anuncia leilão online de 35 diamantes angolanos com 10,80 quilates",
      "url": "https://forbesafricalusofona.com/sodiam-anuncia-leilao-online-de-35-diamantes-angolanos-com-1080-quilates/",
      "source": "Forbes África",
      "_key": "accd683966fafa65"
    },
    {
      "title": "Produção industrial cresce 6,5% no primeiro trimestre de 2026 em Cabo Verde",
      "url": "https://forbesafricalusofona.com/producao-industrial-cresce-65-no-primeiro-trimestre-de-2026-em-cabo-verde/",
      "source": "Forbes África",
      "_key": "c682de64f490406c"
    },
    {
      "title": "Uni-CV e Universidade de Macau assinam acordo de mobilidade de estudantes",
      "url": "https://forbesafricalusofona.com/uni-cv-e-universidade-de-macau-assinam-acordo-de-mobilidade-de-estudantes/",
      "source": "Forbes África",
      "_key": "b5d408f335182bbe"
    },
    {
      "title": "Cruz Vermelha de Angola reitera fortalecimento do sistema de saúde",
      "url": "https://forbesafricalusofona.com/cruz-vermelha-de-angola-reitera-fortalecimento-do-sistema-de-saude/",
      "source": "Forbes África",
      "_key": "1e04d9dc851c3a08"
    },
    {
      "title": "Angola propõe fundo internacional para promover justiça reparatória em ÁfricaPorPedro Mbinza",
      "url": "https://forbesafricalusofona.com/angola-propoe-fundo-internacional-para-promover-justica-reparatoria-em-africa/",
      "source": "Forbes África",
      "_key": "b27e06b55fcc8f0c"
    },
    {
      "title": "Francisco Teixeira denuncia alegada tentativa de atentado em Malanje e acusa militantes do MPLA",
      "url": "https://holdonangola.com/francisco-teixeira-denuncia-alegada-tentativa-de-atentado-em-malanje-e-acusa-militantes-do-mpla/",
      "source": "Hold On Angola",
      "_key": "20b6886491ba5eb9"
    },
    {
      "title": "ANATA garante transporte gratuito durante funeral das vítimas do quádruplo homicídio no Bairro Paraíso",
      "url": "https://holdonangola.com/anata-garante-transporte-gratuito-durante-funeral-das-vitimas-do-quadruplo-homicidio-no-bairro-paraiso/",
      "source": "Hold On Angola",
      "_key": "2f1f0add604c7983"
    },
    {
      "title": "África surpreende no Mundial e Cabo Verde torna-se símbolo da afirmação do futebol africano",
      "url": "https://jornaloguardiao.com/2026/06/22/africa-surpreende-no-mundial-e-cabo-verde-torna-se-simbolo-da-afirmacao-do-futebol-africano/",
      "source": "Jornal O Guardião",
      "_key": "6a57921c3042d591"
    },
    {
      "title": "Sodiam anuncia leilão online de 35 diamantes angolanos com 10,80 quilates",
      "url": "https://jornaloguardiao.com/2026/06/22/sodiam-anuncia-leilao-online-de-35-diamantes-angolanos-com-1080-quilates/",
      "source": "Jornal O Guardião",
      "_key": "435d01848a4fc8b3"
    },
    {
      "title": "Ex-PM cabo-verdiano Ulisses Correia e Silva deixa política ativa",
      "url": "https://jornaloguardiao.com/2026/06/22/ex-pm-cabo-verdiano-ulisses-correia-e-silva-deixa-politica-ativa/",
      "source": "Jornal O Guardião",
      "_key": "cb3d9ea81a780006"
    },
    {
      "title": "Novo primeiro-ministro de Cabo Verde promete “resultados, sem desculpas”",
      "url": "https://jornaloguardiao.com/2026/06/22/novo-primeiro-ministro-de-cabo-verde-promete-resultados-sem-desculpas/",
      "source": "Jornal O Guardião",
      "_key": "ad55883441722f5a"
    },
    {
      "title": "Egipto conquista primeira vitória em Mundiais e assume liderança isolada do Grupo G",
      "url": "https://jornaloguardiao.com/2026/06/22/egipto-conquista-primeira-vitoria-em-mundiais-e-assume-lideranca-isolada-do-grupo-g/",
      "source": "Jornal O Guardião",
      "_key": "611f8b84dbc7964d"
    },
    {
      "title": "Mundial2026: Marrocos vence Escócia e salta à condição para líder do Grupo C",
      "url": "https://jornaloguardiao.com/2026/06/22/mundial2026-marrocos-vence-escocia-e-salta-a-condicao-para-lider-do-grupo-c/",
      "source": "Jornal O Guardião",
      "_key": "04df951a23c6942d"
    },
    {
      "title": "Irão e EUA criam “célula de gestão de conflitos” para pôr fim a combates no Líbano",
      "url": "https://jornaloguardiao.com/2026/06/22/irao-e-eua-criam-celula-de-gestao-de-conflitos-para-por-fim-a-combates-no-libano/",
      "source": "Jornal O Guardião",
      "_key": "206f21512fbd60d4"
    },
    {
      "title": "Quatro aeroportos de Moscovo encerrados devido a ataques com drones",
      "url": "https://jornaloguardiao.com/2026/06/22/quatro-aeroportos-de-moscovo-encerrados-devido-a-ataques-com-drones/",
      "source": "Jornal O Guardião",
      "_key": "05636409174f3e80"
    },
    {
      "title": "Primeiro-ministro britânico confirma especulação e anuncia demissão",
      "url": "https://jornaloguardiao.com/2026/06/22/primeiro-ministro-britanico-confirma-especulacao-e-anuncia-demissao/",
      "source": "Jornal O Guardião",
      "_key": "0635990ddeea8144"
    },
    {
      "title": "ONU rejeita que UE transfira as suas obrigações com migrantes para países terceiros",
      "url": "https://jornaloguardiao.com/2026/06/22/onu-rejeita-que-ue-transfira-as-suas-obrigacoes-com-migrantes-para-paises-terceiros/",
      "source": "Jornal O Guardião",
      "_key": "f71d28c8264e9526"
    },
    {
      "title": "Segunda-feira, 22 de Junho, 2026",
      "url": "",
      "source": "Jornal O Guardião",
      "_key": "t_9cf4ff6dfd6999"
    },
    {
      "title": " África surpreende no Mundial e Cabo Verde torna-se símbolo da afirmação do futebol africano ",
      "url": "",
      "source": "Jornal O Guardião",
      "_key": "t_29fa0ab2c61c54"
    },
    {
      "title": " Sodiam anuncia leilão online de 35 diamantes angolanos com 10,80 quilates ",
      "url": "",
      "source": "Jornal O Guardião",
      "_key": "t_b337c88e1b84b1"
    },
    {
      "title": " Ex-PM cabo-verdiano Ulisses Correia e Silva deixa política ativa ",
      "url": "",
      "source": "Jornal O Guardião",
      "_key": "t_8ccb9cc7e57a81"
    },
    {
      "title": " Novo primeiro-ministro de Cabo Verde promete “resultados, sem desculpas” ",
      "url": "",
      "source": "Jornal O Guardião",
      "_key": "t_fa399e4f9542da"
    },
    {
      "title": " Egipto conquista primeira vitória em Mundiais e assume liderança isolada do Grupo G ",
      "url": "",
      "source": "Jornal O Guardião",
      "_key": "t_19899daa0d8a3c"
    },
    {
      "title": " Mundial2026: Marrocos vence Escócia e salta à condição para líder do Grupo C ",
      "url": "",
      "source": "Jornal O Guardião",
      "_key": "t_4541534bd4a26d"
    },
    {
      "title": " Irão e EUA criam “célula de gestão de conflitos” para pôr fim a combates no Líbano ",
      "url": "",
      "source": "Jornal O Guardião",
      "_key": "t_1aa09410edcaa4"
    },
    {
      "title": " Quatro aeroportos de Moscovo encerrados devido a ataques com drones ",
      "url": "",
      "source": "Jornal O Guardião",
      "_key": "t_4b99171bf7ff7c"
    },
    {
      "title": " Primeiro-ministro britânico confirma especulação e anuncia demissão ",
      "url": "",
      "source": "Jornal O Guardião",
      "_key": "t_b091e789fe89f0"
    },
    {
      "title": " ONU rejeita que UE transfira as suas obrigações com migrantes para países terceiros ",
      "url": "",
      "source": "Jornal O Guardião",
      "_key": "t_65da17691e5564"
    },
    {
      "title": "Destaque MIREX lamenta morte do embaixador Carlos de Lemos Dias aos 64 anos O Ministério das Relações Exteriores (MIREX) manifestou, hoje, profundo pesar pelo falecimento do embaixador de Angola em Cuba, Carlos de Lemos Dias, ocorrido este domingo, numa unidade hospitalar da cidade do Panamá, vítima de doença, aos 64 anos. ",
      "url": "https://www.jornaldeangola.ao/noticias/1/pol%C3%ADtica/679124/mirex-lamenta-morte-do-embaixador-carlos-de-lemos-dias-aos-64-anos-",
      "source": "Jornal de Angola",
      "_key": "e204310e46318ce4"
    },
    {
      "title": "Destaque Manuel Homem enaltece modernização e dedicação dos efectivos no 47.º aniversárioO ministro do Interior, Manuel Homem, reafirmou, hoje, o compromisso com a modernização, a inovação e a excelência institucional, durante a mensagem alusiva ao 47.º aniversário do MININT. ",
      "url": "https://www.jornaldeangola.ao/noticias/3/sociedade/679123/manuel-homem-enaltece-moderniza%C3%A7%C3%A3o-e-dedica%C3%A7%C3%A3o-dos-efectivos-no-47.%C2%BA-anivers%C3%A1rio",
      "source": "Jornal de Angola",
      "_key": "1b1abaa04388f52d"
    },
    {
      "title": "Bombeiros registam seis mortos e 34 feridos durante o fim de semanaSeis pessoas morreram e outras 34 ficaram feridas durante o fim de semana em diferentes ocorrências registadas em várias províncias do país, informou esta segunda-feira o Serviço de Proteção Civil e Bombeiros (SPCB).",
      "url": "https://www.jornaldeangola.ao/noticias/3/sociedade/679121/bombeiros-registam-seis-mortos-e-34-feridos-durante-o-fim-de-semana",
      "source": "Jornal de Angola",
      "_key": "0fdd6c9ecf4d7614"
    },
    {
      "title": "Destaque Presidente João Lourenço realiza visita privada ao BrasilO Chefe de Estado, João Lourenço, desloca-se, hoje, 22, à República Federativa do Brasil, para cumprir uma visita de carácter privado.",
      "url": "https://www.jornaldeangola.ao/noticias/1/pol%C3%ADtica/679130/presidente-jo%C3%A3o-louren%C3%A7o-realiza-visita-privada-ao-brasil",
      "source": "Jornal de Angola",
      "_key": "c6bf277b03710286"
    },
    {
      "title": "Destaque Conselho de Ministros aprecia acordo de financiamento com a CoreiaO Conselho de Ministros apreciou, hoje, para envio à Assembleia Nacional, o Projecto de Resolução que aprova o Acordo-Quadro entre Angola e a República da Coreia, relativo aos Empréstimos do Fundo de Cooperação para o Desenvolvimento Económico (EDCF).",
      "url": "https://www.jornaldeangola.ao/noticias/1/pol%C3%ADtica/679127/conselho-de-ministros-aprecia-acordo-de-financiamento-com-a-coreia",
      "source": "Jornal de Angola",
      "_key": "96e47853b916c6a9"
    },
    {
      "title": "Mundo Primeiro-ministro britânico Keir Starmer anuncia demissão ",
      "url": "https://www.jornaldeangola.ao/noticias/10/mundo/679129/primeiro-ministro-brit%C3%A2nico-keir-starmer-anuncia-demiss%C3%A3o",
      "source": "Jornal de Angola",
      "_key": "7c6295a134c71291"
    },
    {
      "title": "Mundo Ébola: Número de mortes sobe para 254 na RDC ",
      "url": "https://www.jornaldeangola.ao/noticias/10/mundo/679128/%C3%A9bola:-n%C3%BAmero-de-mortes-sobe-para-254-na-rdc",
      "source": "Jornal de Angola",
      "_key": "c8931cd45e6a9043"
    },
    {
      "title": "Sociedade “Hospital em uma Caixa” reforça aposta na inovação tecnológica na Saúde ",
      "url": "https://www.jornaldeangola.ao/noticias/3/sociedade/679126/%E2%80%9Chospital-em-uma-caixa%E2%80%9D-refor%C3%A7a-aposta-na-inova%C3%A7%C3%A3o-tecnol%C3%B3gica-na-sa%C3%BAde",
      "source": "Jornal de Angola",
      "_key": "eb613eda10f484ea"
    },
    {
      "title": "Sociedade MININT celebra 47 anos com tributo aos efectivos que serviram a Pátria ",
      "url": "https://www.jornaldeangola.ao/noticias/3/sociedade/679125/minint-celebra-47-anos-com-tributo-aos-efectivos-que-serviram-a-p%C3%A1tria",
      "source": "Jornal de Angola",
      "_key": "2fad0f399d68a420"
    },
    {
      "title": "Sociedade Bernardeth Mabungo: a angolana que leva a Kizomba ao mundo ",
      "url": "https://www.jornaldeangola.ao/noticias/3/sociedade/679103/bernardeth-mabungo:-a-angolana-que-leva-a-kizomba-ao-mundo",
      "source": "Jornal de Angola",
      "_key": "67f2f25c0dd47fcf"
    },
    {
      "title": "Regiões Requerentes em Cabinda aguardam até 10 dias para receber o documento ",
      "url": "https://www.jornaldeangola.ao/noticias/2/regi%C3%B5es/679096/requerentes-em-cabinda-aguardam-at%C3%A9-10-dias-para-receber-o-documento",
      "source": "Jornal de Angola",
      "_key": "04b1797ede590f99"
    },
    {
      "title": "Regiões Posto móvel de Identificação Civil emite 800 Bilhetes de Identidade em Okaholo ",
      "url": "https://www.jornaldeangola.ao/noticias/2/regi%C3%B5es/679095/posto-m%C3%B3vel-de-identifica%C3%A7%C3%A3o-civil-emite-800-bilhetes-de-identidade-em-okaholo",
      "source": "Jornal de Angola",
      "_key": "ca130e66521a746c"
    },
    {
      "title": "Economia Passageiros da TAAG vão ter preços mais flexibilizados ",
      "url": "https://www.jornaldeangola.ao/noticias/4/economia/679087/passageiros-da-taag-v%C3%A3o-ter-pre%C3%A7os-mais-flexibilizados",
      "source": "Jornal de Angola",
      "_key": "603461c5215cc12d"
    },
    {
      "title": "Economia Projecto coloca mandioca como produto de exportação ",
      "url": "https://www.jornaldeangola.ao/noticias/4/economia/679085/projecto-coloca-mandioca-como-produto-de-exporta%C3%A7%C3%A3o",
      "source": "Jornal de Angola",
      "_key": "76e0dd1c7f90a790"
    },
    {
      "title": "Política Cidadãos eleitores no Cazengo incentivados à prova de vida ",
      "url": "https://www.jornaldeangola.ao/noticias/1/pol%C3%ADtica/679072/cidad%C3%A3os-eleitores-no-cazengo-incentivados-%C3%A0-prova-de-vida",
      "source": "Jornal de Angola",
      "_key": "4a459090e886ba75"
    },
    {
      "title": "Política Cimeira das Civilizações agendada para sábado ",
      "url": "https://www.jornaldeangola.ao/noticias/1/pol%C3%ADtica/679071/cimeira-das-civiliza%C3%A7%C3%B5es-agendada-para-s%C3%A1bado-",
      "source": "Jornal de Angola",
      "_key": "af468b5493bc66c8"
    },
    {
      "title": "Política Filomena Delgado destaca potencial económico do país ",
      "url": "https://www.jornaldeangola.ao/noticias/1/pol%C3%ADtica/679070/filomena-delgado-destaca-potencial-econ%C3%B3mico-do-pa%C3%ADs",
      "source": "Jornal de Angola",
      "_key": "5d1d6e1ac11a5d02"
    },
    {
      "title": "10:41 / 22 jun. 2026 Marcos Garcia toma posse como vice-governador do Cuanza-Norte ",
      "url": "https://www.jornaldeangola.ao/noticias/1/pol%C3%ADtica/679115/marcos-garcia-toma-posse-como-vice-governador-do-cuanza-norte",
      "source": "Jornal de Angola",
      "_key": "2e48c903d55487d1"
    },
    {
      "title": "Angola e Brasil iniciam diálogo para a modernização da JustiçaLuanda acolhe acolhe a partir de hoje, na Escola Nacional de Administração e Políticas Públicas (ENAPP), o 1.º Diálogo Judicial Angola-Brasil, com vista a promover o intercâmbio de conhecimentos, experiências e boas práticas entre os respectivos sistemas judiciais.",
      "url": "https://www.jornaldeangola.ao/noticias/0/%20/679061/angola-e-brasil-iniciam-di%C3%A1logo--para-a-moderniza%C3%A7%C3%A3o-da-justi%C3%A7a",
      "source": "Jornal de Angola",
      "_key": "ef5baa57336d06f4"
    },
    {
      "title": "As vantagens do testemunho ético do cristão em sociedade [I]",
      "url": "https://www.jornaldeangola.ao/noticias/9/opini%C3%A3o/679093/as-vantagens--do-testemunho-%C3%A9tico-do-crist%C3%A3o-em-sociedade-%5Bi%5D",
      "source": "Jornal de Angola",
      "_key": "8c3ea5325c296be7"
    },
    {
      "title": "Economia / Há 4 horas Unitel detalha privatização nos próximos sete dias ",
      "url": "https://www.jornaldeangola.ao/noticias/4/economia/679091/unitel-detalha-privatiza%C3%A7%C3%A3o-nos-pr%C3%B3ximos-sete-dias",
      "source": "Jornal de Angola",
      "_key": "258899c2a0df9a76"
    },
    {
      "title": "Economia / Há 4 horas Bié: Camacupa ganha em breve três novas infra-estruturas ",
      "url": "https://www.jornaldeangola.ao/noticias/4/economia/679089/bi%C3%A9:-camacupa-ganha-em-breve-tr%C3%AAs-novas-infra-estruturas",
      "source": "Jornal de Angola",
      "_key": "e6384ffd3caa48a2"
    },
    {
      "title": "Economia / Há 4 horas Aliko Dangote e Samaila Zubairu participam no ASIF em Luanda ",
      "url": "https://www.jornaldeangola.ao/noticias/4/economia/679088/aliko-dangote-e-samaila-zubairu-participam-no-asif-em-luanda",
      "source": "Jornal de Angola",
      "_key": "71aa54c8ee9fb8df"
    },
    {
      "title": "Mundo22/06/2026Irão interrompe negociações com os Estados Unidos ",
      "url": "https://www.jornaldeangola.ao/noticias/10/mundo/679104/ir%C3%A3o-interrompe-negocia%C3%A7%C3%B5es-com-os-estados-unidos-",
      "source": "Jornal de Angola",
      "_key": "6286fce7f4841885"
    },
    {
      "title": "Mundo22/06/2026Gana recebe espólio do período colonial",
      "url": "https://www.jornaldeangola.ao/noticias/10/mundo/679099/gana-recebe-esp%C3%B3lio-do-per%C3%ADodo-colonial",
      "source": "Jornal de Angola",
      "_key": "70da5136888a147a"
    },
    {
      "title": "Mundo22/06/2026Madagáscar: Rejeitada destituição do Chefe de Estado",
      "url": "https://www.jornaldeangola.ao/noticias/10/mundo/679098/madag%C3%A1scar:-rejeitada-destitui%C3%A7%C3%A3o-do-chefe-de-estado",
      "source": "Jornal de Angola",
      "_key": "b4348b3729b11e8a"
    },
    {
      "title": "Mundo22/06/2026Uganda critica restrições impostas às viagens aéreas",
      "url": "https://www.jornaldeangola.ao/noticias/10/mundo/679097/uganda-critica-restri%C3%A7%C3%B5es-impostas-%C3%A0s-viagens-a%C3%A9reas",
      "source": "Jornal de Angola",
      "_key": "91683f7f342f382f"
    },
    {
      "title": "Sociedade Premium 22/06/2026Mais de 70 mil alunos da 12.ª classe participam a partir de hoje nos exames nacionais",
      "url": "https://www.jornaldeangola.ao/noticias/3/sociedade/679064/mais-de-70-mil--alunos-da-12.%C2%AA-classe-participam-a-partir--de-hoje-nos-exames--nacionais",
      "source": "Jornal de Angola",
      "_key": "7c3925b971aa6097"
    },
    {
      "title": "Sociedade21/06/2026Queda de placa no Estádio da Cidadela expõe degradação da infra-estrutura",
      "url": "https://www.jornaldeangola.ao/noticias/3/sociedade/679052/queda-de-placa-no-est%C3%A1dio-da-cidadela-exp%C3%B5e-degrada%C3%A7%C3%A3o-da-infra-estrutura",
      "source": "Jornal de Angola",
      "_key": "22fb94d78f2af593"
    },
    {
      "title": "SODIAM Launches Online Auction of 35 Special Diamond Stones in Luanda Today22/06/2026",
      "url": "https://www.negociosdeangola.com/en/sodiam-launches-online-auction-of-35-special-diamond-stones-in-luanda-today/",
      "source": "Negócios de Angola",
      "_key": "49388297f921207a"
    },
    {
      "title": "Dangote Says His Wealth Exceeds Forbes Estimates",
      "url": "https://www.negociosdeangola.com/en/dangote-says-his-wealth-exceeds-forbes-estimates/",
      "source": "Negócios de Angola",
      "_key": "cba41b28ce5d2352"
    },
    {
      "title": "AGT Requires Invoices and Delivery Notes for the Transportation of Agricultural Products and Fish",
      "url": "https://www.negociosdeangola.com/en/?post_type=post&p=9989",
      "source": "Negócios de Angola",
      "_key": "3d4832f0c55e41bc"
    },
    {
      "title": "Difficult Access to Credit in Angola Pushes Thousands of Angolans to Buy Homes in Portugal",
      "url": "https://www.negociosdeangola.com/en/?post_type=post&p=9942",
      "source": "Negócios de Angola",
      "_key": "c9c9bb1876e1c01c"
    },
    {
      "title": "Embaixador de Angola em Cuba morre aos 64 anos no Panamá...",
      "url": "https://www.novojornal.co.ao/politica/detalhe/embaixador-de-angola-em-cuba-morre-aos-64-anos-no-panama-vitima-de-doenca-72724.html",
      "source": "Novo Jornal",
      "_key": "99fafa44f5e20066"
    },
    {
      "title": "MININT garante estar a equipar PN e SIC com meios tecnológicos...",
      "url": "https://www.novojornal.co.ao/politica/detalhe/minint-garante-estar-a-equipar-pn-e-sic-com-meios-tecnologicos-para-reforcar-seguranca-publica-e-combater-crimes-informaticos-72722.html",
      "source": "Novo Jornal",
      "_key": "7f62210601e86a36"
    },
    {
      "title": "Ébola: Número de mortes na RDC sobe para 254",
      "url": "https://www.novojornal.co.ao/sociedade/detalhe/ebola-numero-de-mortes-na-rdc-sobe-para-254-72719.html",
      "source": "Novo Jornal",
      "_key": "0c4bdf0f277da8e9"
    },
    {
      "title": "Detido confessa autoria do crime que vitimou família...",
      "url": "https://www.novojornal.co.ao/sociedade/detalhe/detido-confessa-ser-o-autor-do-crime-que-vitimou-familia-no-paraiso-sic-detem-mais-dois-comparsas-populares-incendeiam-casa-do-homicida-72717.html",
      "source": "Novo Jornal",
      "_key": "255ee4bfc342d647"
    },
    {
      "title": "Estádio da Cidadela com sinais visíveis de degradação...",
      "url": "https://www.novojornal.co.ao/sociedade/detalhe/estadio-da-cidadela-com-sinais-visiveis-de-degradacao-apos-placa-do-segundo-anel-cair-este-domingo-72711.html",
      "source": "Novo Jornal",
      "_key": "906185472d8956ec"
    },
    {
      "title": "Sodiam vai leiloar 35 diamantes com 10,80 quilates",
      "url": "https://www.novojornal.co.ao/economia/detalhe/sodiam-vai-leiloar-35-diamantes-com-1080-quilates-72705.html",
      "source": "Novo Jornal",
      "_key": "d8a83084d083576a"
    },
    {
      "title": "Médio Oriente: Irão interrompe negociações depois de...",
      "url": "https://www.novojornal.co.ao/internacional/detalhe/medio-oriente-irao-interrompe-negociacoes-depois-de-novas-ameacas-e-mensagem-insultuosa-de-trump-72713.html",
      "source": "Novo Jornal",
      "_key": "e31335d2ddb2da62"
    },
    {
      "title": "Mundial 2026: 92 anos depois, Faraós quebram amarras...",
      "url": "https://www.novojornal.co.ao/desporto/detalhe/mundial-2026-92-anos-depois-faraos-quebram-amarras-de-1934-e-sobem-ao-trono-do-grupo-g-72708.html",
      "source": "Novo Jornal",
      "_key": "9e85c5fd27a15a97"
    },
    {
      "title": "Mundial 2026: Memorável! Tubarão Hélio encalha Uruguai...",
      "url": "https://www.novojornal.co.ao/desporto/detalhe/mundial-2026-memoravel-tubarao-helio-encalha-uruguai-em-miami-e-cabo-verde-agita-aguas-do-grupo-h-2-2-72702.html",
      "source": "Novo Jornal",
      "_key": "c0afe34841bd6be2"
    },
    {
      "title": "Mundial 2026: Belgas não passam pelo Estreito de Alireza...",
      "url": "https://www.novojornal.co.ao/desporto/detalhe/mundial-2026-belgas-nao-passam-pelo-estreito-de-alireza-beiranvand-72701.html",
      "source": "Novo Jornal",
      "_key": "60f48f7c37d72d40"
    },
    {
      "title": "Namibe na rede global do conhecimento",
      "url": "https://www.novojornal.co.ao/opiniao/detalhe/namibe-na-rede-global-do-conhecimento-72703.html",
      "source": "Novo Jornal",
      "_key": "ec3cba0bd74ef490"
    },
    {
      "title": "\"Makas\" no Cofre de Previdência da Polícia: Tribunal anula decisão do comandante-geral que tinha destituído a direcção eleita por \"má gestão\"",
      "url": "https://www.novojornal.co.ao/sociedade/detalhe/makas-no-cofre-de-previdencia-da-policia-tribunal-anula-decisao-do-comandante-geral-que-tinha-destituido-a-direccao-eleita-por-ma-gestao-72726.html",
      "source": "Novo Jornal",
      "_key": "49823791f813f2e0"
    },
    {
      "title": "EXPANSÃO EM DIRECTO: O FOSSO ESTÁ A AUMENTAR. Crédito ao sector privado em Angola seis vezes abaixo da média da SADC.",
      "url": "https://marginal.co.ao/programas/expansao-em-directo?ep=72718",
      "source": "Novo Jornal",
      "_key": "b636f60ad041b3c7"
    },
    {
      "title": "LUANDA DOWNTOWN  ",
      "url": "https://marginal.co.ao/programas/luanda-downtown?ep=72721",
      "source": "Novo Jornal",
      "_key": "76859e5491ebf513"
    },
    {
      "title": "PONTO & CONTRAPONTO  ",
      "url": "https://marginal.co.ao/programas/ponto-de-vista?ep=72695",
      "source": "Novo Jornal",
      "_key": "5acbef97a5a1224e"
    },
    {
      "title": "ROCK MARGINAL: ONDE O SILÊNCIO ACABA.  ",
      "url": "https://marginal.co.ao/programas/rock-marginal?ep=72716",
      "source": "Novo Jornal",
      "_key": "be6cd31c5de5076d"
    },
    {
      "title": "DOMINGO NA MARGINAL: PILARES DA APOSENTADORIA.  ",
      "url": "https://marginal.co.ao/programas/domingo-na-marginal?ep=72699",
      "source": "Novo Jornal",
      "_key": "2eff9189d160a34c"
    },
    {
      "title": "MAKKAS NA SANZALA: OPINIÃO DESALINHADA.  ",
      "url": "https://marginal.co.ao/programas/makkas-na-sanzala?ep=72689",
      "source": "Novo Jornal",
      "_key": "2bd2ac5ac6b85d16"
    },
    {
      "title": "MAGAZINE MARGINAL: Agenda Cultural e Lazer.  ",
      "url": "https://marginal.co.ao/programas/magazine-marginal?ep=72680",
      "source": "Novo Jornal",
      "_key": "959291bfad230ece"
    },
    {
      "title": "Luanda: Três mortos e nove feridos em dez acidentes durante o fim-de-semana",
      "url": "https://www.novojornal.co.ao/sociedade/detalhe/luanda-tres-mortos-e-nove-feridos-em-dez-acidentes-durante-o-fim-de-semana-72710.html",
      "source": "Novo Jornal",
      "_key": "0039551bfc664730"
    },
    {
      "title": "Mundial 2026: Redemoinho espanhol varre \"falcões verdes\" em Atlanta",
      "url": "https://www.novojornal.co.ao/desporto/detalhe/mundial-2026-redemoinho-espanhol-varre-falcoes-verdes-em-atlanta-72698.html",
      "source": "Novo Jornal",
      "_key": "7043b79aab0f0653"
    },
    {
      "title": "Mundial 2026: Equipas correm para primeira vitória nos grupos G e H",
      "url": "https://www.novojornal.co.ao/desporto/detalhe/mundial-2026-equipas-correm-para-primeira-vitoria-nos-grupos-g-e-h-72697.html",
      "source": "Novo Jornal",
      "_key": "3cb723e0bc3cd4a6"
    },
    {
      "title": "Presidente da República desloca-se hoje ao Brasil para visita privada",
      "url": "https://www.opais.ao/politica/presidente-da-republica-desloca-se-hoje-ao-brasil-para-visita-privada/",
      "source": "O País",
      "_key": "9f71c9450d22ccc9"
    },
    {
      "title": "Conselho de Ministros aprecia incentivos fiscais para blocos petrolíferos",
      "url": "https://www.opais.ao/politica/conselho-de-ministros-aprecia-incentivos-fiscais-para-blocos-petroliferos/",
      "source": "O País",
      "_key": "e10011c481e7a643"
    },
    {
      "title": "Téte António defende uma diplomacia virada para o conhecimento e capaz de aproximar universidades e centros de investigação",
      "url": "https://www.opais.ao/politica/tete-antonio-defende-uma-diplomacia-virada-para-o-conhecimento-e-capaz-de-aproximar-universidades-e-centros-de-investigacao/",
      "source": "O País",
      "_key": "acf8c733567223ca"
    },
    {
      "title": "MPLA e UNITA reforçam diálogo institucional em Luanda",
      "url": "https://www.opais.ao/politica/mpla-e-unita-reforcam-dialogo-institucional-em-luanda/",
      "source": "O País",
      "_key": "79a44813b774bc16"
    },
    {
      "title": "Refinaria de Cabinda produziu mais de 450 mil barris de Óleo Combustível Pesado desde inauguração em 2025",
      "url": "https://www.opais.ao/economia/refinaria-de-cabinda-produziu-mais-de-450-mil-barris-de-oleo-combustivel-pesado-desde-inauguracao-em-2025/",
      "source": "O País",
      "_key": "a80c91224bf5297a"
    },
    {
      "title": "Keir Starmer demite-se do cargo de primeiro-ministro do Reino Unido",
      "url": "https://www.opais.ao/mundo/keir-starmer-demite-se-do-cargo-de-primeiro-ministro-do-reino-unido/",
      "source": "O País",
      "_key": "eb1bd98aabe650e0"
    },
    {
      "title": "Mais de seis mil alunos na província do Uíge participam dos Exames Nacionais",
      "url": "https://www.opais.ao/ultima_hora/mais-de-seis-mil-alunos-na-provincia-do-uige-participam-dos-exames-nacionais/",
      "source": "O País",
      "_key": "1e98705ed986ee2c"
    },
    {
      "title": "Morreu o embaixador de Angola em Cuba aos 64 anos de idade",
      "url": "https://www.opais.ao/politica/morreu-o-embaixador-de-angola-em-cuba-aos-64-anos-de-idade/",
      "source": "O País",
      "_key": "89caff10e24c31aa"
    },
    {
      "title": "A violência contra a criança em Angola: responsabilidade familiar, social e penal",
      "url": "https://www.opais.ao/opiniao/a-violencia-contra-a-crianca-em-angola-responsabilidade-familiar-social-e-penal/",
      "source": "O País",
      "_key": "66a76be697ca139c"
    },
    {
      "title": "O relógio da justiça laboral",
      "url": "https://www.opais.ao/opiniao/o-relogio-da-justica-laboral/",
      "source": "O País",
      "_key": "1b2e5f109093d40b"
    },
    {
      "title": "O futuro da comunicação em Angola não será apenas digital, será credível",
      "url": "https://www.opais.ao/opiniao/o-futuro-da-comunicacao-em-angola-nao-sera-apenas-digital-sera-credivel/",
      "source": "O País",
      "_key": "47bda7554c56d2c0"
    },
    {
      "title": "É de hoje… Casas para os sinistrados em Benguela",
      "url": "https://www.opais.ao/opiniao/e-de-hoje-casas-para-os-sinistrados-em-benguela/",
      "source": "O País",
      "_key": "5a7c87ee0fb7873f"
    },
    {
      "title": "Estudo de Sandra Mainsel sobre literacia digital integra colectânea científica internacional",
      "url": "https://www.opais.ao/opiniao/estudo-de-sandra-mainsel-sobre-literacia-digital-integra-colectanea-cientifica-internacional/",
      "source": "O País",
      "_key": "fe18c025df478f94"
    },
    {
      "title": "SIC desmantela associação criminosa envolvida em trocas ilícitas de cartões multicaixa em Benguela",
      "url": "https://www.opais.ao/ultima_hora/sic-desmantela-associacao-criminosa-envolvida-em-trocas-ilicitas-de-cartoes-multicaixa-em-benguela/",
      "source": "O País",
      "_key": "c9ed975fc35929f6"
    },
    {
      "title": "Ministério do Interior homenageia efectivos tombados em defesa da Pátria",
      "url": "https://www.opais.ao/ultima_hora/ministerio-do-interior-homenageia-efectivos-tombados-em-defesa-da-patria/",
      "source": "O País",
      "_key": "c201e72bb348345d"
    },
    {
      "title": "Presidente da República aprova mais de 100 mil milhões de kwanzas para acomodar vítimas das cheias em Benguela",
      "url": "https://www.opais.ao/politica/presidente-da-republica-aprova-mais-de-100-mil-milhoes-de-kwanzas-para-acomodar-vitimas-das-cheias-em-benguela/",
      "source": "O País",
      "_key": "d7c6ccc58525d6cb"
    },
    {
      "title": "SIC esclarece quadruplo homicídio no bairro Paraíso",
      "url": "https://www.opais.ao/ultima_hora/sic-esclarece-quadruplo-homicidio-no-bairro-paraiso/",
      "source": "O País",
      "_key": "494a6e8b8ad16d9f"
    },
    {
      "title": "Mais de 500 automobilistas multados em Luanda durante o fim-de-semana",
      "url": "https://www.opais.ao/ultima_hora/mais-de-500-automobilistas-multados-em-luanda-durante-o-fim-de-semana/",
      "source": "O País",
      "_key": "0ee47d5aa4c75e84"
    },
    {
      "title": "Manuel Homem destaca modernização e compromisso com a segurança no 47.º aniversário do MININT",
      "url": "https://www.opais.ao/ultima_hora/manuel-homem-destaca-modernizacao-e-compromisso-com-a-seguranca-no-47-o-aniversario-do-minint/",
      "source": "O País",
      "_key": "c1108ba22dfe6f04"
    },
    {
      "title": "Pastor detido na Lunda-Norte por alegado abuso sexual de uma jovem internada para tratamentos espirituais",
      "url": "https://www.opais.ao/ultima_hora/pastor-detido-na-lunda-norte-por-alegado-abuso-sexual-de-uma-jovem-internada-para-tratamentos-espirituais/",
      "source": "O País",
      "_key": "f7debb6e0b487a0f"
    },
    {
      "title": "Luanda acolhe primeiro Diálogo Judicial entre Angola e Brasil",
      "url": "https://www.opais.ao/ultima_hora/luanda-acolhe-primeiro-dialogo-judicial-entre-angola-e-brasil/",
      "source": "O País",
      "_key": "2900a730e1297f37"
    },
    {
      "title": "França alerta serviços de emergência por onda de calor",
      "url": "https://www.opais.ao/mundo/franca-alerta-servicos-de-emergencia-por-onda-de-calor/",
      "source": "O País",
      "_key": "bb73a1d26d548c51"
    },
    {
      "title": "Papa pede aos líderes que “acolham vítimas de perseguição”",
      "url": "https://www.opais.ao/mundo/papa-pede-aos-lideres-que-acolham-vitimas-de-perseguicao/",
      "source": "O País",
      "_key": "1c2185a559802c62"
    },
    {
      "title": "Circuito Internacional de Teatro acolhe mais de 60 grupos em Luanda e Namibe",
      "url": "https://www.opais.ao/cultura/circuito-internacional-de-teatro-acolhe-mais-de-60-grupos-em-luanda-e-namibe/",
      "source": "O País",
      "_key": "2dee1efad945961f"
    },
    {
      "title": "Angola aguarda entre Novembro e Dezembro reconhecimento mundial do Semba pela UNESCO",
      "url": "https://www.opais.ao/cultura/angola-aguarda-entre-novembro-e-dezembro-reconhecimento-mundial-do-semba-pela-unesco/",
      "source": "O País",
      "_key": "9c1ecc8928653a3c"
    },
    {
      "title": "Lateral da Tunísia em lágrimas: “Viemos disputar um Mundial com jogadores que nunca jogaram juntos”",
      "url": "https://www.opais.ao/desporto/lateral-da-tunisia-em-lagrimas-viemos-disputar-um-mundial-com-jogadores-que-nunca-jogaram-juntos/",
      "source": "O País",
      "_key": "f5367a0f97a40c1d"
    },
    {
      "title": "Espanha dá passo de gigante rumo a outra fase após “esmagar” Arábia Saudita",
      "url": "https://www.opais.ao/desporto/espanha-da-passo-de-gigante-rumo-a-outra-fase-apos-esmagar-arabia-saudita/",
      "source": "O País",
      "_key": "8d8faf6b5b70a73c"
    },
    {
      "title": "Argentina de Messi com tarefa facilitada diante da Áustria",
      "url": "https://www.opais.ao/desporto/argentina-de-messi-com-tarefa-facilitada-diante-da-austria/",
      "source": "O País",
      "_key": "0dc5e7e5de014c85"
    },
    {
      "title": "Mundial 2026: Cabo Verde empata diante do Uruguai e “pisca” passe aos 16 avos-de-final",
      "url": "https://www.opais.ao/desporto/mundial-2026-cabo-verde-empata-diante-do-uruguai-e-pisca-passe-aos-16-avos-de-final/",
      "source": "O País",
      "_key": "1192fa8ceced2fd5"
    },
    {
      "title": "MINJUD promete pronunciar-se hoje sobre desabamento de uma parte da bancada do Estádio Nacional da Cidadela",
      "url": "https://www.opais.ao/desporto/minjud-promete-pronunciar-se-hoje-sobre-desabamento-de-uma-parte-da-bancada-do-estadio-nacional-da-cidadela/",
      "source": "O País",
      "_key": "7681c30a88ab94df"
    },
    {
      "title": "Dois anos depois, Angola continua retida na ‘lista cinzenta’ do...",
      "url": "https://valoreconomico.co.ao/artigo/dois-anos-depois-angola-continua-retida-na-lista-cinzenta-do-gafi",
      "source": "Valor Económico",
      "_key": "7ba0063bd595a44c"
    },
    {
      "title": "Cultura adjudica por convite 160 milhões de kwanzas à produtora...",
      "url": "https://valoreconomico.co.ao/artigo/cultura-adjudica-por-convite-160-milhoes-de-kwanzas-a-produtora-geracao-80-para-promover-cinema",
      "source": "Valor Económico",
      "_key": "dcfbe9468b2ef859"
    },
    {
      "title": "Lucro da estatal SODIAM tombam 68% em 2025,apesar de ano...",
      "url": "https://valoreconomico.co.ao/artigo/lucro-da-estatal-sodiam-tombam-68-em-2025-apesar-de-ano-recorde-nas-vendas",
      "source": "Valor Económico",
      "_key": "d818880dfa511829"
    }
  ]
}