{
  "date": "2026-05-02",
  "total_extracted": 1585,
  "total_new": 8,
  "total_existing": 1577,
  "articles": [
    {
      "title": "Crédito online gera queixas de ameaças e uso abusivo de dados pessoais",
      "url": "https://correiokianda.info/credito-online-gera-queixas-de-ameacas-e-uso-abusivo-de-dados-pessoais/",
      "source": "Correio Kianda",
      "_key": "8408d1fdaa81be74"
    },
    {
      "title": "Retirada de tropas dos EUA da Alemanha reacende alertas sobre desintegração da NATO, diz PM polonês",
      "url": "https://correiokianda.info/retirada-de-tropas-dos-eua-da-alemanha-reacende-alertas-sobre-desintegracao-da-nato-diz-pm-polones/",
      "source": "Correio Kianda",
      "_key": "94c1bd2a70b79ca2"
    },
    {
      "title": "Administração Trump eleva para 25% tarifas sobre carros europeus",
      "url": "https://correiokianda.info/administracao-trump-eleva-para-25-tarifas-sobre-carros-europeus/",
      "source": "Correio Kianda",
      "_key": "1182ec15a64b5af2"
    },
    {
      "title": "Ressaca do Dia do Trabalhador: celebrar ontem, sobreviver hoje",
      "url": "https://correiokianda.info/ressaca-do-dia-do-trabalhador-celebrar-ontem-sobreviver-hoje/",
      "source": "Correio Kianda",
      "_key": "d4d6599f249a1bb5"
    },
    {
      "title": "Última hora Destacada cooperação com Japão na modernização de infra-estruturas de saúde",
      "url": "https://www.jornaldeangola.ao/noticias/3/sociedade/675247/destacada-coopera%C3%A7%C3%A3o-com-jap%C3%A3o-na-moderniza%C3%A7%C3%A3o-de-infra-estruturas-de-sa%C3%BAde",
      "source": "Jornal de Angola",
      "_key": "ac1d4d9782b769e0"
    },
    {
      "title": "‎Região 5 acelera fase final de preparação da RASA 2026",
      "url": "https://www.opais.ao/desporto/regiao-5-acelera-fase-final-de-preparacao-da-rasa-2026/",
      "source": "O País",
      "_key": "79e43337594c3007"
    },
    {
      "title": "Petro e Sporting de Luanda começam hoje corrida ao título",
      "url": "https://www.opais.ao/desporto/petro-e-sporting-de-luanda-comecam-hoje-corrida-ao-titulo/",
      "source": "O País",
      "_key": "a308c47f1c40fb76"
    },
    {
      "title": "TAAG anuncia regresso de aviões após manutenção e garante voos...",
      "url": "https://valoreconomico.co.ao/artigo/taag-anuncia-regresso-de-avioes-apos-manutencao-e-garante-voos-domesticos",
      "source": "Valor Económico",
      "_key": "01165175fe8aa864"
    }
  ]
}