{
  "date": "2026-04-16",
  "total_new": 47,
  "total_filtered": 3,
  "scored_by": "keyword",
  "articles": [
    {
      "title": "ZEE registers investments valued at 1.9 billion kwanzas in 7 years",
      "url": "https://www.angop.ao/en/noticias/economia/zona-economica-regista-investimentos-avaliados-em-1.9-bilioes-de-kwanzas-em-sete-anos/",
      "source": "ANGOP",
      "_key": "d4e4b6b9cf098a55",
      "score": 5,
      "title_cn": "ZEE 7年内投资价值19亿宽扎"
    },
    {
      "title": "Homem paga 30 mil kwanzas para assassinar vizinha por disputa de terras no Uíge",
      "url": "https://correiokianda.info/homem-paga-30-mil-kwanzas-para-assassinar-vizinha-por-disputa-de-terras-no-uige/",
      "source": "Correio Kianda",
      "_key": "8022e5687fb50494",
      "score": 5,
      "title_cn": "原标题 ： 维吾尔族男子支付 3 万宽扎因土地纠纷杀害邻居"
    },
    {
      "title": "Crescimento económico baixo e inflação alta colocam Angola na cauda...",
      "url": "https://valoreconomico.co.ao/artigo/crescimento-economico-baixo-e-inflacao-alta-colocam-angola-na-cauda-da-regiao-14077",
      "source": "Valor Económico",
      "_key": "2dce75b85917ad87",
      "score": 5,
      "title_cn": "低经济增长和高通货膨胀使安哥拉落在后面。"
    }
  ]
}